object_detection_model/__init__.py
object_detection_model/model.py
object_detection_model/model_files/__init__.py
object_detection_model/model_files/coco.names
object_detection_model/model_files/frozen_inference_graph.pb
object_detection_model/model_files/ssd_mobilenet_v3_large_coco_2020_01_14.pbtxt
object_detection_model-0.0.8.dist-info/LICENSE.txt
object_detection_model-0.0.8.dist-info/METADATA
object_detection_model-0.0.8.dist-info/WHEEL
object_detection_model-0.0.8.dist-info/top_level.txt
object_detection_model-0.0.8.dist-info/RECORD
